[
  {
    "name": "Омлет с молоком",
    "ingredients": [
      {
        "nomenclature": "Яйца куриные",
        "quantity": 3
      },
      {
        "nomenclature": "Молоко",
        "quantity": 150
      },
      {
        "nomenclature": "Соль",
        "quantity": 3
      },
      {
        "nomenclature": "Сливочное масло",
        "quantity": 20
      },
      {
        "nomenclature": "Перец черный",
        "quantity": 2
      }
    ],
    "steps": [
      "Подготовка яиц: Яйца куриные достаньте заранее, чтобы они достигли комнатной температуры",
      "Взбивание основы: В миске взбейте яйца с солью и черным перцем до легкой пены и однородной консистенции",
      "Добавление молока: Постепенно влейте молоко, аккуратно перемешивая. Избегайте интенсивного взбивания",
      "Подготовка сковороды: В сковороде растопите сливочное масло, равномерно распределите по всей поверхности",
      "Выпекание: Вылейте яично-молочную смесь в разогретую сковороду. Накройте крышкой",
      "Приготовление: Готовьте на среднем огне 7-10 минут. Омлет готов, когда края золотятся, а середина пропечена",
      "Подача: Немного дайте омлету остыть в сковороде, затем аккуратно сверните или разрежьте на порции. Подавайте сразу после приготовления"
    ]
  }
]